{"type":"FeatureCollection","features":[{"geometry":{"type":"Polygon","coordinates":[[[126.00130,-20.30342],[126.00130,-20.46819],[125.85938,-20.46819],[125.85938,-20.30342],[126.00130,-20.30342]]]},"type":"Feature","id":"7953591fbf","clipped":true,"properties":{"lga_code14":"53220"}},{"geometry":{"type":"Polygon","coordinates":[[[126.00130,-20.46819],[126.00130,-20.30342],[126.03516,-20.30342],[126.03516,-20.46819],[126.00130,-20.46819]]]},"type":"Feature","id":"84648a63f3","clipped":true,"properties":{"lga_code14":"53920"}}]}