{"type":"FeatureCollection","features":[{"geometry":{"type":"Polygon","coordinates":[[[128.32031,-31.37476],[128.49609,-31.37351],[128.49609,-31.50363],[128.32031,-31.50363],[128.32031,-31.37476]]]},"type":"Feature","id":"635e581835","clipped":true,"properties":{"lga_code14":"53080"}},{"geometry":{"type":"Polygon","coordinates":[[[128.49609,-31.37351],[128.32031,-31.37476],[128.32031,-31.35364],[128.49609,-31.35364],[128.49609,-31.37351]]]},"type":"Feature","id":"653ece50ac","clipped":true,"properties":{"lga_code14":"54280"}}]}