{"type":"FeatureCollection","features":[{"geometry":{"type":"Polygon","coordinates":[[[124.45312,-31.38496],[124.62891,-31.38358],[124.62891,-31.50363],[124.45312,-31.50363],[124.45312,-31.38496]]]},"type":"Feature","id":"635e581835","clipped":true,"properties":{"lga_code14":"53080"}},{"geometry":{"type":"Polygon","coordinates":[[[124.62891,-31.38358],[124.45312,-31.38496],[124.45312,-31.35364],[124.62891,-31.35364],[124.62891,-31.38358]]]},"type":"Feature","id":"653ece50ac","clipped":true,"properties":{"lga_code14":"54280"}}]}