{"type":"FeatureCollection","features":[{"geometry":{"type":"Polygon","coordinates":[[[114.80690,-25.00597],[114.80697,-25.16517],[114.78516,-25.16517],[114.78516,-25.00597],[114.80690,-25.00597]]]},"type":"Feature","id":"8a579ec12b","clipped":true,"properties":{"lga_code14":"51540"}},{"geometry":{"type":"Polygon","coordinates":[[[114.80697,-25.16517],[114.80690,-25.00597],[114.96094,-25.00597],[114.96094,-25.16517],[114.80697,-25.16517]]]},"type":"Feature","id":"8afb71bca6","clipped":true,"properties":{"lga_code14":"58470"}}]}