{"type":"FeatureCollection","features":[{"geometry":{"type":"Polygon","coordinates":[[[117.24083,-28.14950],[117.24079,-27.99440],[117.24609,-27.99440],[117.24609,-28.14950],[117.24083,-28.14950]]]},"type":"Feature","id":"0356d8d104","clipped":true,"properties":{"lga_code14":"55810"}},{"geometry":{"type":"Polygon","coordinates":[[[117.24079,-27.99440],[117.24083,-28.14950],[117.07031,-28.14950],[117.07031,-27.99440],[117.24079,-27.99440]]]},"type":"Feature","id":"d2b742edc0","clipped":true,"properties":{"lga_code14":"59350"}}]}