{"type":"FeatureCollection","features":[{"geometry":{"type":"Polygon","coordinates":[[[120.15243,-27.99440],[120.15716,-27.68353],[120.23437,-27.68353],[120.23437,-27.99440],[120.15243,-27.99440]]]},"type":"Feature","id":"ab4fa9f64a","clipped":true,"properties":{"sa2_main11":"508031203"}},{"geometry":{"type":"Polygon","coordinates":[[[120.15716,-27.68353],[120.15243,-27.99440],[119.88281,-27.99440],[119.88281,-27.68353],[120.15716,-27.68353]]]},"type":"Feature","id":"195c0224c8","clipped":true,"properties":{"sa2_main11":"508051215"}}]}