{"type":"FeatureCollection","features":[{"geometry":{"type":"Polygon","coordinates":[[[131.48437,-24.13676],[131.83594,-24.13619],[131.83594,-24.20689],[131.48437,-24.20689],[131.48437,-24.13676]]]},"type":"Feature","id":"79bb02870c","clipped":true,"properties":{"sa2_main11":"702011050"}},{"geometry":{"type":"Polygon","coordinates":[[[131.83594,-24.13619],[131.48437,-24.13676],[131.48437,-23.88584],[131.83594,-23.88584],[131.83594,-24.13619]]]},"type":"Feature","id":"361cb8da28","clipped":true,"properties":{"sa2_main11":"702011053"}}]}