{"type":"FeatureCollection","features":[{"geometry":{"type":"Polygon","coordinates":[[[121.96082,-28.45903],[121.96127,-28.30438],[121.99219,-28.30438],[121.99219,-28.45903],[121.96082,-28.45903]]]},"type":"Feature","id":"a124f99b1b","clipped":true,"properties":{"lga_code14":"54970"}},{"geometry":{"type":"Polygon","coordinates":[[[121.96127,-28.30438],[121.96082,-28.45903],[121.81641,-28.45903],[121.81641,-28.30438],[121.96127,-28.30438]]]},"type":"Feature","id":"ec63b11576","clipped":true,"properties":{"lga_code14":"55040"}}]}