{"type":"FeatureCollection","features":[{"geometry":{"type":"Polygon","coordinates":[[[144.7821,-33.1376],[144.7982,-33.0362],[144.8437,-33.0413],[144.8437,-33.1376],[144.7821,-33.1376]]]},"type":"Feature","id":"6952474631","clipped":true,"properties":{"lga_code14":"11600"}},{"geometry":{"type":"Polygon","coordinates":[[[144.8437,-33.0413],[144.7982,-33.0362],[144.7821,-33.1376],[144.1406,-33.1376],[144.1406,-32.5468],[144.8437,-32.5468],[144.8437,-33.0413]]]},"type":"Feature","id":"00cd0b6a39","clipped":true,"properties":{"lga_code14":"11700"}}]}