{"type":"FeatureCollection","features":[{"geometry":{"type":"Polygon","coordinates":[[[128.49609,-26.74547],[128.50175,-26.74547],[128.67187,-26.74532],[128.67187,-26.74561],[128.49609,-26.74547]]]},"type":"Feature","id":"a124f99b1b","clipped":true,"properties":{"lga_code14":"54970"}},{"geometry":{"type":"Polygon","coordinates":[[[128.67187,-26.74532],[128.49609,-26.74547],[128.49609,-26.58853],[128.67187,-26.58853],[128.67187,-26.74532]]]},"type":"Feature","id":"6317e82d10","clipped":true,"properties":{"lga_code14":"56620"}}]}