{"type":"FeatureCollection","features":[{"geometry":{"type":"Polygon","coordinates":[[[124.6680,-23.4403],[125.0013,-23.4320],[125.1563,-23.4320],[125.1563,-23.8858],[124.6680,-23.8858],[124.6680,-23.4403]]]},"type":"Feature","id":"ab4fa9f64a","clipped":true,"properties":{"sa2_main11":"508031203"}},{"geometry":{"type":"Polygon","coordinates":[[[124.4531,-23.4417],[124.6680,-23.4403],[124.6680,-23.8858],[124.4531,-23.8858],[124.4531,-23.4417]]]},"type":"Feature","id":"195c0224c8","clipped":true,"properties":{"sa2_main11":"508051215"}},{"geometry":{"type":"Polygon","coordinates":[[[125.1563,-23.4320],[124.4531,-23.4417],[124.4531,-23.2413],[125.1563,-23.2413],[125.1563,-23.4320]]]},"type":"Feature","id":"5c1e5cf791","clipped":true,"properties":{"sa2_main11":"508061219"}}]}