{"type":"FeatureCollection","features":[{"geometry":{"type":"Polygon","coordinates":[[[117.77344,-29.61247],[117.94922,-29.61246],[117.94922,-29.68805],[117.77344,-29.68805],[117.77344,-29.61247]]]},"type":"Feature","id":"19ae96279b","clipped":true,"properties":{"lga_code14":"55880"}},{"geometry":{"type":"Polygon","coordinates":[[[117.94922,-29.61246],[117.93205,-29.61243],[117.93205,-29.53523],[117.94922,-29.53523],[117.94922,-29.61246]]]},"type":"Feature","id":"399046406b","clipped":true,"properties":{"lga_code14":"57630"}},{"geometry":{"type":"Polygon","coordinates":[[[117.93205,-29.53523],[117.93205,-29.61243],[117.77344,-29.61247],[117.77344,-29.53523],[117.93205,-29.53523]]]},"type":"Feature","id":"d2b742edc0","clipped":true,"properties":{"lga_code14":"59350"}}]}