{"type":"FeatureCollection","features":[{"geometry":{"type":"Polygon","coordinates":[[[123.75000,-31.38741],[123.92578,-31.38719],[123.92578,-31.50363],[123.75000,-31.50363],[123.75000,-31.38741]]]},"type":"Feature","id":"635e581835","clipped":true,"properties":{"lga_code14":"53080"}},{"geometry":{"type":"Polygon","coordinates":[[[123.92578,-31.38719],[123.75000,-31.38741],[123.75000,-31.35364],[123.92578,-31.35364],[123.92578,-31.38719]]]},"type":"Feature","id":"653ece50ac","clipped":true,"properties":{"lga_code14":"54280"}}]}