{"type":"FeatureCollection","features":[{"geometry":{"type":"Polygon","coordinates":[[[144.8437,-33.0413],[144.7982,-33.0362],[144.7821,-33.1376],[144.1406,-33.1376],[144.1406,-32.5468],[144.8437,-32.5468],[144.8437,-33.0413]]]},"type":"Feature","id":"99dec1ee61","clipped":true,"properties":{"sa4_code11":"105"}},{"geometry":{"type":"Polygon","coordinates":[[[144.7821,-33.1376],[144.7982,-33.0362],[144.8437,-33.0413],[144.8437,-33.1376],[144.7821,-33.1376]]]},"type":"Feature","id":"e0716d19a4","clipped":true,"properties":{"sa4_code11":"109"}}]}