{"type":"FeatureCollection","features":[{"geometry":{"type":"Polygon","coordinates":[[[140.96437,-34.45222],[140.96342,-34.30714],[140.97656,-34.30714],[140.97656,-34.45222],[140.96437,-34.45222]]]},"type":"Feature","id":"6d311c1a36","clipped":true,"properties":{"lga_code14":"24780"}},{"geometry":{"type":"Polygon","coordinates":[[[140.80078,-34.32319],[140.96354,-34.32279],[140.96437,-34.45222],[140.80078,-34.45222],[140.80078,-34.32319]]]},"type":"Feature","id":"ae2aa499df","clipped":true,"properties":{"lga_code14":"43790"}},{"geometry":{"type":"Polygon","coordinates":[[[140.96342,-34.30714],[140.96354,-34.32279],[140.80078,-34.32319],[140.80078,-34.30714],[140.96342,-34.30714]]]},"type":"Feature","id":"95bd343ed9","clipped":true,"properties":{"lga_code14":"46670"}}]}