{"type":"FeatureCollection","features":[{"geometry":{"type":"Polygon","coordinates":[[[121.77906,-27.05913],[121.77905,-26.90248],[121.81641,-26.90248],[121.81641,-27.05913],[121.77906,-27.05913]]]},"type":"Feature","id":"a124f99b1b","clipped":true,"properties":{"lga_code14":"54970"}},{"geometry":{"type":"Polygon","coordinates":[[[121.77905,-26.90248],[121.77906,-27.05913],[121.64062,-27.05913],[121.64062,-26.90248],[121.77905,-26.90248]]]},"type":"Feature","id":"6a4a55c180","clipped":true,"properties":{"lga_code14":"59250"}}]}