{"type":"FeatureCollection","features":[{"geometry":{"type":"Polygon","coordinates":[[[142.10596,-24.04646],[142.12408,-23.88584],[142.20703,-23.88584],[142.20703,-24.04646],[142.10596,-24.04646]]]},"type":"Feature","id":"523f45aa89","clipped":true,"properties":{"lga_code14":"30450"}},{"geometry":{"type":"Polygon","coordinates":[[[142.12408,-23.88584],[142.10596,-24.04646],[142.03125,-24.04646],[142.03125,-23.88584],[142.12408,-23.88584]]]},"type":"Feature","id":"cd78e2d6b3","clipped":true,"properties":{"lga_code14":"32750"}}]}