{"type":"FeatureCollection","features":[{"geometry":{"type":"Polygon","coordinates":[[[140.99993,-29.53523],[140.99963,-29.22889],[141.32813,-29.22889],[141.32813,-29.53523],[140.99993,-29.53523]]]},"type":"Feature","id":"164a77a1f2","clipped":true,"properties":{"lga_code14":"19399"}},{"geometry":{"type":"Polygon","coordinates":[[[140.99963,-29.22889],[140.99993,-29.53523],[140.97656,-29.53523],[140.97656,-29.22889],[140.99963,-29.22889]]]},"type":"Feature","id":"b5760cfa11","clipped":true,"properties":{"lga_code14":"49399"}}]}